Workbook

Sheet TITULAR
A1: Gigs IRPF | C1: 1. DADOS DO TITULAR
A2: organizador do imposto de renda
A3: =HYPERLINK("#TITULAR!D8","TITULAR") -> TITULAR | C3: Preencha os campos amarelos. A coluna STATUS avisa o que está pendente ou inválido.
A4: =HYPERLINK("#INFORMES!D8","INFORMES") -> INFORMES
A5: =HYPERLINK("#GUIA!C8","GUIA & LINKS") -> GUIA & LINKS
C7: IDENTIFICAÇÃO
A8: PROGRESSO | C8: NOME COMPLETO | D8: Maria Exemplo da Silva | E8: =IF(D8="","Pendente",IF(ISNUMBER(FIND(" ",TRIM(D8))),"OK","Inválido")) -> OK
A9: ="Titular: "&TEXT(IFERROR(COUNTIF(TITULAR!$E$8:$E$29,"OK")/(COUNTIF(TITULAR!$E$8:$E$29,"OK")+COUNTIF(TITULAR!$E$8:$E$29,"Pendente")+COUNTIF(TITULAR!$E$8:$E$29,"Inválido")),0),"0%") -> Titular: 100% | C9: CPF | D9: 52998224725 | E9: =IF(D9="","Pendente",IF(ISNUMBER(D9),IF(IFERROR(AND(D9<=99999999999,VALUE(MID(TEXT(D9,"00000000000"),10,1))=MOD(MOD(SUMPRODUCT(--MID(TEXT(D9,"00000000000"),{1,2,3,4,5,6,7,8,9},1),{10,9,8,7,6,5,4,3,2})*10,11),10),VALUE(MID(TEXT(D9,"00000000000"),11,1))=MOD(MOD(SUMPRODUCT(--MID(TEXT(D9,"00000000000"),{1,2,3,4,5,6,7,8,9,10},1),{11,10,9,8,7,6,5,4,3,2})*10,11),10),TEXT(D9,"00000000000")<>REPT(LEFT(TEXT(D9,"00000000000"),1),11)),FALSE()),"OK","Inválido"),"Inválido")) -> OK | F9: =IF(AND(ISNUMBER(D9),D9<=99999999999),"***.***.***-"&RIGHT(TEXT(D9,"00000000000"),2),"") -> ***.***.***-25
A10: ="Informes: "&COUNTIF(INFORMES!O8:O37,"OK")&" de "&COUNTA(INFORMES!E8:E37)&" ok" -> Informes: 2 de 3 ok | C10: DATA DE NASCIMENTO | D10: 37023 | E10: =IF(D10="","Pendente",IF(AND(ISNUMBER(D10),D10<=TODAY()),"OK","Inválido")) -> OK | F10: =IF(AND(ISNUMBER(D10),D10<=TODAY()),DATEDIF(D10,TODAY(),"Y")&" anos e "&DATEDIF(D10,TODAY(),"YM")&" meses","") -> 25 anos e 4 meses
A11: ="Checklist: "&GUIA!E5 -> Checklist: 2 de 8 | C11: TÍTULO DE ELEITOR | D11: 123456789012 | E11: =IF(D11="","—","OK") -> OK
C12: ESTADO CIVIL | D12: Casado(a) | E12: =IF(D12="","Pendente","OK") -> OK
C13: CÔNJUGE | D13: João Exemplo da Silva | E13: =IF(OR(D12="Casado(a)",D12="União estável"),IF(D13="","Pendente","OK"),"—") -> OK
C15: CONTATO E ENDEREÇO
C16: CEP | D16: 25211280 | E16: =IF(D16="","Pendente",IF(AND(ISNUMBER(D16),D16>=1000000,D16<=99999999),"OK","Inválido")) -> OK
C17: ENDEREÇO | D17: Rua das Flores, 100, apto 12 | E17: =IF(D17="","Pendente","OK") -> OK
C18: CIDADE | D18: Rio de Janeiro | E18: =IF(D18="","Pendente","OK") -> OK
C19: UF | D19: RJ | E19: =IF(D19="","Pendente","OK") -> OK
C20: CELULAR | D20: 21900000000 | E20: =IF(D20="","Pendente",IF(AND(ISNUMBER(D20),D20>=10000000000,D20<=99999999999),"OK","Inválido")) -> OK
C21: E-MAIL | D21: maria.exemplo@email.com | E21: =IF(D21="","Pendente",IF(AND(ISNUMBER(FIND("@",D21)),FIND("@",D21)>1,ISNUMBER(FIND(".",D21,FIND("@",D21))),ISERROR(FIND(" ",D21))),"OK","Inválido")) -> OK
C23: QUESTIONÁRIO (SIM / NÃO)
C24: DECLAROU NO ANO ANTERIOR? | D24: Sim | E24: =IF(D24="","Pendente","OK") -> OK
C25: MUDOU DE ENDEREÇO? | D25: Não | E25: =IF(D25="","Pendente","OK") -> OK
C26: POSSUI DEPENDENTES? | D26: Sim | E26: =IF(D26="","Pendente","OK") -> OK
C27: Nº DE DEPENDENTES | D27: 2 | E27: =IF(D26="Sim",IF(D27="","Pendente","OK"),"—") -> OK
C28: RESIDE NO EXTERIOR? | D28: Não | E28: =IF(D28="","Pendente","OK") -> OK
C29: RECEBEU RENDA DO EXTERIOR? | D29: Não | E29: =IF(D29="","Pendente","OK") -> OK
C33: Os dados desta aba são fictícios, só de exemplo !
C34: Cônjuge e Nº de dependentes só são cobrados quando fazem sentido (viram cinza quando não se aplicam).

Sheet INFORMES
A1: Gigs IRPF | C1: 2. INFORMES DE RENDIMENTOS
A2: organizador do imposto de renda | C2: Um informe por linha. Tipo, ficha, competência e status se preenchem sozinhos. Use as setas do cabeçalho para filtrar.
A3: =HYPERLINK("#TITULAR!D8","TITULAR") -> TITULAR | D3: ANO-BASE | E3: TOTAL RECEBIDO | F3: IR RETIDO | G3: SEM COMPROVANTE | H3: % RETIDO
A4: =HYPERLINK("#INFORMES!D8","INFORMES") -> INFORMES | D4: 2026 | E4: =SUM(H8:H37) -> 6860.9 | F4: =SUM(I8:I37) -> 568 | G4: =COUNTIF(J8:J37,"Não") -> 1 | H4: =IF(E4=0,0,F4/E4) -> 0.082787972
A5: =HYPERLINK("#GUIA!C8","GUIA & LINKS") -> GUIA & LINKS
C7: Nº | D7: Data do recebimento | E7: Fonte pagadora | F7: CNPJ da fonte | G7: Tipo de rendimento | H7: Valor (R$) | I7: IR retido (R$) | J7: Comprovante? | K7: Competência | L7: Ficha do IRPF | M7: Tributação | N7: Dias desde receb. | O7: Status
A8: PROGRESSO | C8: =IF(COUNTA(D8:J8)=0,"",ROW()-7) -> 1 | D8: 46086 | E8: Empresa Exemplo Ltda | F8: 11222333000181 | G8: Salário / Pró-labore | H8: 5200 | I8: 380.5 | J8: Sim | K8: =IF(ISNUMBER(D8),RIGHT("0"&MONTH(D8),2)&"/"&YEAR(D8),"") -> 03/2026 | L8: =IF(G8="","",IFERROR(VLOOKUP(G8,GUIA!$C$16:$E$25,2,FALSE()),"Tipo não cadastrado")) -> Rendimentos Tributáveis Recebidos de Pessoa Jurídica | M8: =IF(G8="","",IFERROR(VLOOKUP(G8,GUIA!$C$16:$E$25,3,FALSE()),"—")) -> Tributável (tabela progressiva) | N8: =IF(ISNUMBER(D8),IF(D8>TODAY(),0,DATEDIF(D8,TODAY(),"D")),"") -> 217 | O8: =IF(COUNTA(D8:J8)=0,"",IF(OR(D8="",E8="",F8="",G8="",H8=""),"Incompleto",IF(I8>H8,"IR > valor",IF(YEAR(D8)<>$D$4,"Fora do ano-base",IF(J8="Não","Sem comprovante","OK"))))) -> OK
A9: ="Titular: "&TEXT(IFERROR(COUNTIF(TITULAR!$E$8:$E$29,"OK")/(COUNTIF(TITULAR!$E$8:$E$29,"OK")+COUNTIF(TITULAR!$E$8:$E$29,"Pendente")+COUNTIF(TITULAR!$E$8:$E$29,"Inválido")),0),"0%") -> Titular: 100% | C9: =IF(COUNTA(D9:J9)=0,"",ROW()-7) -> 2 | D9: 46188 | E9: Banco Exemplo S.A. | F9: 12345678000195 | G9: Poupança / LCI / LCA | H9: 410.9 | I9: 0 | J9: Sim | K9: =IF(ISNUMBER(D9),RIGHT("0"&MONTH(D9),2)&"/"&YEAR(D9),"") -> 06/2026 | L9: =IF(G9="","",IFERROR(VLOOKUP(G9,GUIA!$C$16:$E$25,2,FALSE()),"Tipo não cadastrado")) -> Rendimentos Isentos e Não Tributáveis | M9: =IF(G9="","",IFERROR(VLOOKUP(G9,GUIA!$C$16:$E$25,3,FALSE()),"—")) -> Isento | N9: =IF(ISNUMBER(D9),IF(D9>TODAY(),0,DATEDIF(D9,TODAY(),"D")),"") -> 115 | O9: =IF(COUNTA(D9:J9)=0,"",IF(OR(D9="",E9="",F9="",G9="",H9=""),"Incompleto",IF(I9>H9,"IR > valor",IF(YEAR(D9)<>$D$4,"Fora do ano-base",IF(J9="Não","Sem comprovante","OK"))))) -> OK
A10: ="Informes: "&COUNTIF(INFORMES!O8:O37,"OK")&" de "&COUNTA(INFORMES!E8:E37)&" ok" -> Informes: 2 de 3 ok | C10: =IF(COUNTA(D10:J10)=0,"",ROW()-7) -> 3 | D10: 46285 | E10: Corretora Exemplo | F10: 98765432000198 | G10: Renda fixa (CDB / Tesouro) | H10: 1250 | I10: 187.5 | J10: Não | K10: =IF(ISNUMBER(D10),RIGHT("0"&MONTH(D10),2)&"/"&YEAR(D10),"") -> 09/2026 | L10: =IF(G10="","",IFERROR(VLOOKUP(G10,GUIA!$C$16:$E$25,2,FALSE()),"Tipo não cadastrado")) -> Rendimentos Sujeitos à Tributação Exclusiva/Definitiva | M10: =IF(G10="","",IFERROR(VLOOKUP(G10,GUIA!$C$16:$E$25,3,FALSE()),"—")) -> Exclusiva na fonte | N10: =IF(ISNUMBER(D10),IF(D10>TODAY(),0,DATEDIF(D10,TODAY(),"D")),"") -> 18 | O10: =IF(COUNTA(D10:J10)=0,"",IF(OR(D10="",E10="",F10="",G10="",H10=""),"Incompleto",IF(I10>H10,"IR > valor",IF(YEAR(D10)<>$D$4,"Fora do ano-base",IF(J10="Não","Sem comprovante","OK"))))) -> Sem comprovante
A11: ="Checklist: "&GUIA!E5 -> Checklist: 2 de 8 | C11: =IF(COUNTA(D11:J11)=0,"",ROW()-7) | K11: =IF(ISNUMBER(D11),RIGHT("0"&MONTH(D11),2)&"/"&YEAR(D11),"") | L11: =IF(G11="","",IFERROR(VLOOKUP(G11,GUIA!$C$16:$E$25,2,FALSE()),"Tipo não cadastrado")) | M11: =IF(G11="","",IFERROR(VLOOKUP(G11,GUIA!$C$16:$E$25,3,FALSE()),"—")) | N11: =IF(ISNUMBER(D11),IF(D11>TODAY(),0,DATEDIF(D11,TODAY(),"D")),"") | O11: =IF(COUNTA(D11:J11)=0,"",IF(OR(D11="",E11="",F11="",G11="",H11=""),"Incompleto",IF(I11>H11,"IR > valor",IF(YEAR(D11)<>$D$4,"Fora do ano-base",IF(J11="Não","Sem comprovante","OK")))))
C12: =IF(COUNTA(D12:J12)=0,"",ROW()-7) | K12: =IF(ISNUMBER(D12),RIGHT("0"&MONTH(D12),2)&"/"&YEAR(D12),"") | L12: =IF(G12="","",IFERROR(VLOOKUP(G12,GUIA!$C$16:$E$25,2,FALSE()),"Tipo não cadastrado")) | M12: =IF(G12="","",IFERROR(VLOOKUP(G12,GUIA!$C$16:$E$25,3,FALSE()),"—")) | N12: =IF(ISNUMBER(D12),IF(D12>TODAY(),0,DATEDIF(D12,TODAY(),"D")),"") | O12: =IF(COUNTA(D12:J12)=0,"",IF(OR(D12="",E12="",F12="",G12="",H12=""),"Incompleto",IF(I12>H12,"IR > valor",IF(YEAR(D12)<>$D$4,"Fora do ano-base",IF(J12="Não","Sem comprovante","OK")))))
C13: =IF(COUNTA(D13:J13)=0,"",ROW()-7) | K13: =IF(ISNUMBER(D13),RIGHT("0"&MONTH(D13),2)&"/"&YEAR(D13),"") | L13: =IF(G13="","",IFERROR(VLOOKUP(G13,GUIA!$C$16:$E$25,2,FALSE()),"Tipo não cadastrado")) | M13: =IF(G13="","",IFERROR(VLOOKUP(G13,GUIA!$C$16:$E$25,3,FALSE()),"—")) | N13: =IF(ISNUMBER(D13),IF(D13>TODAY(),0,DATEDIF(D13,TODAY(),"D")),"") | O13: =IF(COUNTA(D13:J13)=0,"",IF(OR(D13="",E13="",F13="",G13="",H13=""),"Incompleto",IF(I13>H13,"IR > valor",IF(YEAR(D13)<>$D$4,"Fora do ano-base",IF(J13="Não","Sem comprovante","OK")))))
C14: =IF(COUNTA(D14:J14)=0,"",ROW()-7) | K14: =IF(ISNUMBER(D14),RIGHT("0"&MONTH(D14),2)&"/"&YEAR(D14),"") | L14: =IF(G14="","",IFERROR(VLOOKUP(G14,GUIA!$C$16:$E$25,2,FALSE()),"Tipo não cadastrado")) | M14: =IF(G14="","",IFERROR(VLOOKUP(G14,GUIA!$C$16:$E$25,3,FALSE()),"—")) | N14: =IF(ISNUMBER(D14),IF(D14>TODAY(),0,DATEDIF(D14,TODAY(),"D")),"") | O14: =IF(COUNTA(D14:J14)=0,"",IF(OR(D14="",E14="",F14="",G14="",H14=""),"Incompleto",IF(I14>H14,"IR > valor",IF(YEAR(D14)<>$D$4,"Fora do ano-base",IF(J14="Não","Sem comprovante","OK")))))
C15: =IF(COUNTA(D15:J15)=0,"",ROW()-7) | K15: =IF(ISNUMBER(D15),RIGHT("0"&MONTH(D15),2)&"/"&YEAR(D15),"") | L15: =IF(G15="","",IFERROR(VLOOKUP(G15,GUIA!$C$16:$E$25,2,FALSE()),"Tipo não cadastrado")) | M15: =IF(G15="","",IFERROR(VLOOKUP(G15,GUIA!$C$16:$E$25,3,FALSE()),"—")) | N15: =IF(ISNUMBER(D15),IF(D15>TODAY(),0,DATEDIF(D15,TODAY(),"D")),"") | O15: =IF(COUNTA(D15:J15)=0,"",IF(OR(D15="",E15="",F15="",G15="",H15=""),"Incompleto",IF(I15>H15,"IR > valor",IF(YEAR(D15)<>$D$4,"Fora do ano-base",IF(J15="Não","Sem comprovante","OK")))))
C16: =IF(COUNTA(D16:J16)=0,"",ROW()-7) | K16: =IF(ISNUMBER(D16),RIGHT("0"&MONTH(D16),2)&"/"&YEAR(D16),"") | L16: =IF(G16="","",IFERROR(VLOOKUP(G16,GUIA!$C$16:$E$25,2,FALSE()),"Tipo não cadastrado")) | M16: =IF(G16="","",IFERROR(VLOOKUP(G16,GUIA!$C$16:$E$25,3,FALSE()),"—")) | N16: =IF(ISNUMBER(D16),IF(D16>TODAY(),0,DATEDIF(D16,TODAY(),"D")),"") | O16: =IF(COUNTA(D16:J16)=0,"",IF(OR(D16="",E16="",F16="",G16="",H16=""),"Incompleto",IF(I16>H16,"IR > valor",IF(YEAR(D16)<>$D$4,"Fora do ano-base",IF(J16="Não","Sem comprovante","OK")))))
C17: =IF(COUNTA(D17:J17)=0,"",ROW()-7) | K17: =IF(ISNUMBER(D17),RIGHT("0"&MONTH(D17),2)&"/"&YEAR(D17),"") | L17: =IF(G17="","",IFERROR(VLOOKUP(G17,GUIA!$C$16:$E$25,2,FALSE()),"Tipo não cadastrado")) | M17: =IF(G17="","",IFERROR(VLOOKUP(G17,GUIA!$C$16:$E$25,3,FALSE()),"—")) | N17: =IF(ISNUMBER(D17),IF(D17>TODAY(),0,DATEDIF(D17,TODAY(),"D")),"") | O17: =IF(COUNTA(D17:J17)=0,"",IF(OR(D17="",E17="",F17="",G17="",H17=""),"Incompleto",IF(I17>H17,"IR > valor",IF(YEAR(D17)<>$D$4,"Fora do ano-base",IF(J17="Não","Sem comprovante","OK")))))
C18: =IF(COUNTA(D18:J18)=0,"",ROW()-7) | K18: =IF(ISNUMBER(D18),RIGHT("0"&MONTH(D18),2)&"/"&YEAR(D18),"") | L18: =IF(G18="","",IFERROR(VLOOKUP(G18,GUIA!$C$16:$E$25,2,FALSE()),"Tipo não cadastrado")) | M18: =IF(G18="","",IFERROR(VLOOKUP(G18,GUIA!$C$16:$E$25,3,FALSE()),"—")) | N18: =IF(ISNUMBER(D18),IF(D18>TODAY(),0,DATEDIF(D18,TODAY(),"D")),"") | O18: =IF(COUNTA(D18:J18)=0,"",IF(OR(D18="",E18="",F18="",G18="",H18=""),"Incompleto",IF(I18>H18,"IR > valor",IF(YEAR(D18)<>$D$4,"Fora do ano-base",IF(J18="Não","Sem comprovante","OK")))))
C19: =IF(COUNTA(D19:J19)=0,"",ROW()-7) | K19: =IF(ISNUMBER(D19),RIGHT("0"&MONTH(D19),2)&"/"&YEAR(D19),"") | L19: =IF(G19="","",IFERROR(VLOOKUP(G19,GUIA!$C$16:$E$25,2,FALSE()),"Tipo não cadastrado")) | M19: =IF(G19="","",IFERROR(VLOOKUP(G19,GUIA!$C$16:$E$25,3,FALSE()),"—")) | N19: =IF(ISNUMBER(D19),IF(D19>TODAY(),0,DATEDIF(D19,TODAY(),"D")),"") | O19: =IF(COUNTA(D19:J19)=0,"",IF(OR(D19="",E19="",F19="",G19="",H19=""),"Incompleto",IF(I19>H19,"IR > valor",IF(YEAR(D19)<>$D$4,"Fora do ano-base",IF(J19="Não","Sem comprovante","OK")))))
C20: =IF(COUNTA(D20:J20)=0,"",ROW()-7) | K20: =IF(ISNUMBER(D20),RIGHT("0"&MONTH(D20),2)&"/"&YEAR(D20),"") | L20: =IF(G20="","",IFERROR(VLOOKUP(G20,GUIA!$C$16:$E$25,2,FALSE()),"Tipo não cadastrado")) | M20: =IF(G20="","",IFERROR(VLOOKUP(G20,GUIA!$C$16:$E$25,3,FALSE()),"—")) | N20: =IF(ISNUMBER(D20),IF(D20>TODAY(),0,DATEDIF(D20,TODAY(),"D")),"") | O20: =IF(COUNTA(D20:J20)=0,"",IF(OR(D20="",E20="",F20="",G20="",H20=""),"Incompleto",IF(I20>H20,"IR > valor",IF(YEAR(D20)<>$D$4,"Fora do ano-base",IF(J20="Não","Sem comprovante","OK")))))
C21: =IF(COUNTA(D21:J21)=0,"",ROW()-7) | K21: =IF(ISNUMBER(D21),RIGHT("0"&MONTH(D21),2)&"/"&YEAR(D21),"") | L21: =IF(G21="","",IFERROR(VLOOKUP(G21,GUIA!$C$16:$E$25,2,FALSE()),"Tipo não cadastrado")) | M21: =IF(G21="","",IFERROR(VLOOKUP(G21,GUIA!$C$16:$E$25,3,FALSE()),"—")) | N21: =IF(ISNUMBER(D21),IF(D21>TODAY(),0,DATEDIF(D21,TODAY(),"D")),"") | O21: =IF(COUNTA(D21:J21)=0,"",IF(OR(D21="",E21="",F21="",G21="",H21=""),"Incompleto",IF(I21>H21,"IR > valor",IF(YEAR(D21)<>$D$4,"Fora do ano-base",IF(J21="Não","Sem comprovante","OK")))))
C22: =IF(COUNTA(D22:J22)=0,"",ROW()-7) | K22: =IF(ISNUMBER(D22),RIGHT("0"&MONTH(D22),2)&"/"&YEAR(D22),"") | L22: =IF(G22="","",IFERROR(VLOOKUP(G22,GUIA!$C$16:$E$25,2,FALSE()),"Tipo não cadastrado")) | M22: =IF(G22="","",IFERROR(VLOOKUP(G22,GUIA!$C$16:$E$25,3,FALSE()),"—")) | N22: =IF(ISNUMBER(D22),IF(D22>TODAY(),0,DATEDIF(D22,TODAY(),"D")),"") | O22: =IF(COUNTA(D22:J22)=0,"",IF(OR(D22="",E22="",F22="",G22="",H22=""),"Incompleto",IF(I22>H22,"IR > valor",IF(YEAR(D22)<>$D$4,"Fora do ano-base",IF(J22="Não","Sem comprovante","OK")))))
C23: =IF(COUNTA(D23:J23)=0,"",ROW()-7) | K23: =IF(ISNUMBER(D23),RIGHT("0"&MONTH(D23),2)&"/"&YEAR(D23),"") | L23: =IF(G23="","",IFERROR(VLOOKUP(G23,GUIA!$C$16:$E$25,2,FALSE()),"Tipo não cadastrado")) | M23: =IF(G23="","",IFERROR(VLOOKUP(G23,GUIA!$C$16:$E$25,3,FALSE()),"—")) | N23: =IF(ISNUMBER(D23),IF(D23>TODAY(),0,DATEDIF(D23,TODAY(),"D")),"") | O23: =IF(COUNTA(D23:J23)=0,"",IF(OR(D23="",E23="",F23="",G23="",H23=""),"Incompleto",IF(I23>H23,"IR > valor",IF(YEAR(D23)<>$D$4,"Fora do ano-base",IF(J23="Não","Sem comprovante","OK")))))
... C37: =IF(COUNTA(D37:J37)=0,"",ROW()-7) | K37: =IF(ISNUMBER(D37),RIGHT("0"&MONTH(D37),2)&"/"&YEAR(D37),"") | L37: =IF(G37="","",IFERROR(VLOOKUP(G37,GUIA!$C$16:$E$25,2,FALSE()),"Tipo não cadastrado")) | M37: =IF(G37="","",IFERROR(VLOOKUP(G37,GUIA!$C$16:$E$25,3,FALSE()),"—")) | N37: =IF(ISNUMBER(D37),IF(D37>TODAY(),0,DATEDIF(D37,TODAY(),"D")),"") | O37: =IF(COUNTA(D37:J37)=0,"",IF(OR(D37="",E37="",F37="",G37="",H37=""),"Incompleto",IF(I37>H37,"IR > valor",IF(YEAR(D37)<>$D$4,"Fora do ano-base",IF(J37="Não","Sem comprovante","OK")))))
G38: TOTAL (respeita os filtros) | H38: =SUBTOTAL(109,H8:H37) -> 6860.9 | I38: =SUBTOTAL(109,I8:I37) -> 568
D40: LEGENDA
D41: Amarelo = você preenche · Branco = calculado (Competência, Ficha, Tributação, Dias, Status).
D42: As 3 primeiras linhas são exemplos fictícios: apague e use as suas. Há espaço para 30 informes.
D43: Status acusa: dados faltando, IR maior que o valor, data fora do ano-base e comprovante pendente.

Sheet GUIA
A1: Gigs IRPF | C1: 3. GUIA, LINKS E PRAZOS
A2: organizador do imposto de renda
A3: =HYPERLINK("#TITULAR!D8","TITULAR") -> TITULAR
A4: =HYPERLINK("#INFORMES!D8","INFORMES") -> INFORMES | C4: PRAZO DE ENTREGA (edite a data) | D4: FALTAM | E4: CHECKLIST
A5: =HYPERLINK("#GUIA!C8","GUIA & LINKS") -> GUIA & LINKS | C5: 46538 | D5: =IF(C5="","Defina o prazo",IF(TODAY()>C5,"Prazo encerrado",DATEDIF(TODAY(),C5,"D")&" dias")) -> 235 dias | E5: =COUNTIF(E31:E38,"Sim")&" de "&ROWS(E31:E38) -> 2 de 8
C7: LINKS RÁPIDOS (clique para abrir)
A8: PROGRESSO | C8: Meu Imposto de Renda (Receita) | D8: Programa, calendário e orientações oficiais
A9: ="Titular: "&TEXT(IFERROR(COUNTIF(TITULAR!$E$8:$E$29,"OK")/(COUNTIF(TITULAR!$E$8:$E$29,"OK")+COUNTIF(TITULAR!$E$8:$E$29,"Pendente")+COUNTIF(TITULAR!$E$8:$E$29,"Inválido")),0),"0%") -> Titular: 100% | C9: e-CAC (Receita Federal) | D9: Declaração pré-preenchida, pendências e extrato
A10: ="Informes: "&COUNTIF(INFORMES!O8:O37,"OK")&" de "&COUNTA(INFORMES!E8:E37)&" ok" -> Informes: 2 de 3 ok | C10: Consulta de restituição | D10: Veja em qual lote sua restituição entrou
A11: ="Checklist: "&GUIA!E5 -> Checklist: 2 de 8 | C11: Consulta de CNPJ | D11: Confira o CNPJ das fontes pagadoras
C12: Situação cadastral do CPF | D12: Garanta que o CPF está regular
C14: TIPOS DE RENDIMENTO → FICHA DO IRPF
C15: Tipo de rendimento | D15: Ficha do IRPF onde entra | E15: Tributação | F15: Qtd. informes | G15: Total (R$)
C16: Salário / Pró-labore | D16: Rendimentos Tributáveis Recebidos de Pessoa Jurídica | E16: Tributável (tabela progressiva) | F16: =COUNTIF(INFORMES!$G$8:$G$37,C16) -> 1 | G16: =SUMIF(INFORMES!$G$8:$G$37,C16,INFORMES!$H$8:$H$37) -> 5200
C17: Autônomo / Serviços (PF) | D17: Rendimentos Tributáveis Recebidos de PF / Exterior | E17: Tributável (Carnê-Leão) | F17: =COUNTIF(INFORMES!$G$8:$G$37,C17) -> 0 | G17: =SUMIF(INFORMES!$G$8:$G$37,C17,INFORMES!$H$8:$H$37) -> 0
C18: Aluguel recebido (PF) | D18: Rendimentos Tributáveis Recebidos de PF / Exterior | E18: Tributável (Carnê-Leão) | F18: =COUNTIF(INFORMES!$G$8:$G$37,C18) -> 0 | G18: =SUMIF(INFORMES!$G$8:$G$37,C18,INFORMES!$H$8:$H$37) -> 0
C19: 13º salário | D19: Rendimentos Sujeitos à Tributação Exclusiva/Definitiva | E19: Exclusiva na fonte | F19: =COUNTIF(INFORMES!$G$8:$G$37,C19) -> 0 | G19: =SUMIF(INFORMES!$G$8:$G$37,C19,INFORMES!$H$8:$H$37) -> 0
C20: Renda fixa (CDB / Tesouro) | D20: Rendimentos Sujeitos à Tributação Exclusiva/Definitiva | E20: Exclusiva na fonte | F20: =COUNTIF(INFORMES!$G$8:$G$37,C20) -> 1 | G20: =SUMIF(INFORMES!$G$8:$G$37,C20,INFORMES!$H$8:$H$37) -> 1250
C21: Poupança / LCI / LCA | D21: Rendimentos Isentos e Não Tributáveis | E21: Isento | F21: =COUNTIF(INFORMES!$G$8:$G$37,C21) -> 1 | G21: =SUMIF(INFORMES!$G$8:$G$37,C21,INFORMES!$H$8:$H$37) -> 410.9
C22: Fundos imobiliários (FII) | D22: Rendimentos Isentos e Não Tributáveis | E22: Isento (se cumprir as regras) | F22: =COUNTIF(INFORMES!$G$8:$G$37,C22) -> 0 | G22: =SUMIF(INFORMES!$G$8:$G$37,C22,INFORMES!$H$8:$H$37) -> 0
C23: Lucros e dividendos | D23: Rendimentos Isentos e Não Tributáveis | E23: Confira as regras do ano | F23: =COUNTIF(INFORMES!$G$8:$G$37,C23) -> 0 | G23: =SUMIF(INFORMES!$G$8:$G$37,C23,INFORMES!$H$8:$H$37) -> 0
C24: Bolsa de valores (ações) | D24: Renda Variável | E24: Definitiva (DARF) | F24: =COUNTIF(INFORMES!$G$8:$G$37,C24) -> 0 | G24: =SUMIF(INFORMES!$G$8:$G$37,C24,INFORMES!$H$8:$H$37) -> 0
C25: Outros | D25: Verificar a ficha adequada | E25: Verificar | F25: =COUNTIF(INFORMES!$G$8:$G$37,C25) -> 0 | G25: =SUMIF(INFORMES!$G$8:$G$37,C25,INFORMES!$H$8:$H$37) -> 0
E26: TOTAL | F26: =SUM(F16:F25) -> 3 | G26: =SUM(G16:G25) -> 6860.9
C29: CHECKLIST DE DOCUMENTOS (SIM / NÃO)
C30: Documento | D30: Onde conseguir / dica | E30: Tenho em mãos?
C31: Informe de rendimentos do empregador | D31: RH da empresa ou contracheque de dezembro | E31: Sim
C32: Informe de rendimentos bancário | D32: App ou internet banking | E32: Sim
C33: Informe da corretora / investimentos | D33: Área do investidor da corretora | E33: Não
C34: Recibos de despesas médicas | D34: Guarde recibos com CPF/CNPJ do profissional
C35: Despesas com educação | D35: Boletos e recibos da instituição
C36: Previdência privada (PGBL) | D36: Informe do banco ou da seguradora
C37: Dados dos dependentes (CPF e nascimento) | D37: Documentos dos dependentes
C38: Recibo da declaração do ano anterior | D38: Útil para importar dados no programa
